<main>
	<first>
		<word>
			<title>a</title>
			<known>true</known>
		</word>
		<word>
			<title>about</title>
			<known>true</known>
		</word>
		<word>
			<title>after</title>
			<known>true</known>
		</word>
		<word>
			<title>again</title>
			<known>true</known>
		</word>
		<word>
			<title>all</title>
			<known>true</known>
		</word>
		<word>
			<title>am</title>
			<known>true</known>
		</word>
		<word>
			<title>an</title>
			<known>true</known>
		</word>
		<word>
			<title>and</title>
			<known>true</known>
		</word>
		<word>
			<title>another</title>
			<known>true</known>
		</word>
		<word>
			<title>any</title>
			<known>true</known>
		</word>
		<word>
			<title>are</title>
			<known>true</known>
		</word>
		<word>
			<title>as</title>
			<known>true</known>
		</word>
		<word>
			<title>at</title>
			<known>true</known>
		</word>
		<word>
			<title>away</title>
			<known>true</known>
		</word>
		<word>
			<title>back</title>
			<known>true</known>
		</word>
		<word>
			<title>be</title>
			<known>true</known>
		</word>
		<word>
			<title>because</title>
			<known>true</known>
		</word>
		<word>
			<title>been</title>
			<known>true</known>
		</word>
		<word>
			<title>before</title>
			<known>true</known>
		</word>
		<word>
			<title>but</title>
			<known>true</known>
		</word>
		<word>
			<title>by</title>
			<known>true</known>
		</word>
		<word>
			<title>came</title>
			<known>true</known>
		</word>
		<word>
			<title>can</title>
			<known>true</known>
		</word>
		<word>
			<title>come</title>
			<known>true</known>
		</word>
		<word>
			<title>could</title>
			<known>true</known>
		</word>
		<word>
			<title>day</title>
			<known>true</known>
		</word>
		<word>
			<title>did</title>
			<known>true</known>
		</word>
		<word>
			<title>do</title>
			<known>true</known>
		</word>
		<word>
			<title>down</title>
			<known>true</known>
		</word>
		<word>
			<title>even</title>
			<known>true</known>
		</word>
		<word>
			<title>eye</title>
			<known>true</known>
		</word>
		<word>
			<title>face</title>
			<known>true</known>
		</word>
		<word>
			<title>first</title>
			<known>true</known>
		</word>
		<word>
			<title>for</title>
			<known>true</known>
		</word>
		<word>
			<title>from</title>
			<known>true</known>
		</word>
		<word>
			<title>go</title>
			<known>true</known>
		</word>
		<word>
			<title>had</title>
			<known>true</known>
		</word>
		<word>
			<title>has</title>
			<known>true</known>
		</word>
		<word>
			<title>have</title>
			<known>true</known>
		</word>
		<word>
			<title>he</title>
			<known>true</known>
		</word>
		<word>
			<title>her</title>
			<known>true</known>
		</word>
		<word>
			<title>here</title>
			<known>true</known>
		</word>
		<word>
			<title>him</title>
			<known>true</known>
		</word>
		<word>
			<title>himself</title>
			<known>true</known>
		</word>
		<word>
			<title>his</title>
			<known>true</known>
		</word>
		<word>
			<title>how</title>
			<known>true</known>
		</word>
		<word>
			<title>if</title>
			<known>true</known>
		</word>
		<word>
			<title>in</title>
			<known>true</known>
		</word>
		<word>
			<title>into</title>
			<known>true</known>
		</word>
		<word>
			<title>is</title>
			<known>true</known>
		</word>
		<word>
			<title>it</title>
			<known>true</known>
		</word>
		<word>
			<title>its</title>
			<known>true</known>
		</word>
		<word>
			<title>just</title>
			<known>true</known>
		</word>
		<word>
			<title>know</title>
			<known>true</known>
		</word>
		<word>
			<title>last</title>
			<known>true</known>
		</word>
		<word>
			<title>like</title>
			<known>true</known>
		</word>
		<word>
			<title>little</title>
			<known>true</known>
		</word>
		<word>
			<title>made</title>
			<known>true</known>
		</word>
		<word>
			<title>make</title>
			<known>true</known>
		</word>
		<word>
			<title>me</title>
			<known>true</known>
		</word>
		<word>
			<title>might</title>
			<known>true</known>
		</word>
		<word>
			<title>more</title>
			<known>true</known>
		</word>
		<word>
			<title>much</title>
			<known>true</known>
		</word>
		<word>
			<title>must</title>
			<known>true</known>
		</word>
		<word>
			<title>my</title>
			<known>true</known>
		</word>
		<word>
			<title>never</title>
			<known>true</known>
		</word>
		<word>
			<title>no</title>
			<known>true</known>
		</word>
		<word>
			<title>not</title>
			<known>true</known>
		</word>
		<word>
			<title>nothing</title>
			<known>true</known>
		</word>
		<word>
			<title>now</title>
			<known>true</known>
		</word>
		<word>
			<title>of</title>
			<known>true</known>
		</word>
		<word>
			<title>off</title>
			<known>true</known>
		</word>
		<word>
			<title>old</title>
			<known>true</known>
		</word>
		<word>
			<title>on</title>
			<known>true</known>
		</word>
		<word>
			<title>once</title>
			<known>true</known>
		</word>
		<word>
			<title>one</title>
			<known>true</known>
		</word>
		<word>
			<title>only</title>
			<known>true</known>
		</word>
		<word>
			<title>or</title>
			<known>true</known>
		</word>
		<word>
			<title>other</title>
			<known>true</known>
		</word>
		<word>
			<title>out</title>
			<known>true</known>
		</word>
		<word>
			<title>over</title>
			<known>true</known>
		</word>
		<word>
			<title>own</title>
			<known>true</known>
		</word>
		<word>
			<title>same</title>
			<known>true</known>
		</word>
		<word>
			<title>say</title>
			<known>true</known>
		</word>
		<word>
			<title>see</title>
			<known>true</known>
		</word>
		<word>
			<title>seem</title>
			<known>true</known>
		</word>
		<word>
			<title>she</title>
			<known>true</known>
		</word>
		<word>
			<title>should</title>
			<known>true</known>
		</word>
		<word>
			<title>so</title>
			<known>true</known>
		</word>
		<word>
			<title>some</title>
			<known>true</known>
		</word>
		<word>
			<title>still</title>
			<known>true</known>
		</word>
		<word>
			<title>such</title>
			<known>true</known>
		</word>
		<word>
			<title>than</title>
			<known>true</known>
		</word>
		<word>
			<title>that</title>
			<known>true</known>
		</word>
		<word>
			<title>the</title>
			<known>true</known>
		</word>
		<word>
			<title>their</title>
			<known>true</known>
		</word>
		<word>
			<title>them</title>
			<known>true</known>
		</word>
		<word>
			<title>then</title>
			<known>true</known>
		</word>
		<word>
			<title>there</title>
			<known>true</known>
		</word>
		<word>
			<title>these</title>
			<known>true</known>
		</word>
		<word>
			<title>they</title>
			<known>true</known>
		</word>
		<word>
			<title>this</title>
			<known>true</known>
		</word>
		<word>
			<title>time</title>
			<known>true</known>
		</word>
		<word>
			<title>to</title>
			<known>true</known>
		</word>
		<word>
			<title>too</title>
			<known>true</known>
		</word>
		<word>
			<title>two</title>
			<known>true</known>
		</word>
		<word>
			<title>up</title>
			<known>true</known>
		</word>
		<word>
			<title>us</title>
			<known>true</known>
		</word>
		<word>
			<title>very</title>
			<known>true</known>
		</word>
		<word>
			<title>was</title>
			<known>true</known>
		</word>
		<word>
			<title>way</title>
			<known>true</known>
		</word>
		<word>
			<title>we</title>
			<known>true</known>
		</word>
		<word>
			<title>well</title>
			<known>true</known>
		</word>
		<word>
			<title>went</title>
			<known>true</known>
		</word>
		<word>
			<title>were</title>
			<known>true</known>
		</word>
		<word>
			<title>what</title>
			<known>true</known>
		</word>
		<word>
			<title>when</title>
			<known>true</known>
		</word>
		<word>
			<title>which</title>
			<known>true</known>
		</word>
		<word>
			<title>who</title>
			<known>true</known>
		</word>
		<word>
			<title>why</title>
			<known>true</known>
		</word>
		<word>
			<title>will</title>
			<known>true</known>
		</word>
		<word>
			<title>with</title>
			<known>true</known>
		</word>
		<word>
			<title>would</title>
			<known>true</known>
		</word>
		<word>
			<title>you</title>
			<known>true</known>
		</word>
		<word>
			<title>your</title>
			<known>true</known>
		</word>
	</first>
	<second>
		<word>
			<title>able</title>
			<known>true</known>
		</word>
		<word>
			<title>ago</title>
			<known>true</known>
		</word>
		<word>
			<title>almost</title>
			<known>true</known>
		</word>
		<word>
			<title>alone</title>
			<known>true</known>
		</word>
		<word>
			<title>already</title>
			<known>true</known>
		</word>
		<word>
			<title>also</title>
			<known>true</known>
		</word>
		<word>
			<title>always</title>
			<known>true</known>
		</word>
		<word>
			<title>anything</title>
			<known>true</known>
		</word>
		<word>
			<title>ask</title>
			<known>true</known>
		</word>
		<word>
			<title>believe</title>
			<known>true</known>
		</word>
		<word>
			<title>better</title>
			<known>true</known>
		</word>
		<word>
			<title>between</title>
			<known>true</known>
		</word>
		<word>
			<title>big</title>
			<known>true</known>
		</word>
		<word>
			<title>black</title>
			<known>true</known>
		</word>
		<word>
			<title>body</title>
			<known>true</known>
		</word>
		<word>
			<title>both</title>
			<known>true</known>
		</word>
		<word>
			<title>brief</title>
			<known>true</known>
		</word>
		<word>
			<title>brother</title>
			<known>true</known>
		</word>
		<word>
			<title>brought</title>
			<known>true</known>
		</word>
		<word>
			<title>case</title>
			<known>true</known>
		</word>
		<word>
			<title>certain</title>
			<known>true</known>
		</word>
		<word>
			<title>children</title>
			<known>true</known>
		</word>
		<word>
			<title>course</title>
			<known>true</known>
		</word>
		<word>
			<title>death</title>
			<known>true</known>
		</word>
		<word>
			<title>different</title>
			<known>true</known>
		</word>
		<word>
			<title>does</title>
			<known>true</known>
		</word>
		<word>
			<title>done</title>
			<known>true</known>
		</word>
		<word>
			<title>door</title>
			<known>true</known>
		</word>
		<word>
			<title>each</title>
			<known>true</known>
		</word>
		<word>
			<title>earth</title>
			<known>true</known>
		</word>
		<word>
			<title>end</title>
			<known>true</known>
		</word>
		<word>
			<title>energy</title>
			<known>true</known>
		</word>
		<word>
			<title>enough</title>
			<known>true</known>
		</word>
		<word>
			<title>ever</title>
			<known>true</known>
		</word>
		<word>
			<title>every</title>
			<known>true</known>
		</word>
		<word>
			<title>everything</title>
			<known>true</known>
		</word>
		<word>
			<title>fact</title>
			<known>true</known>
		</word>
		<word>
			<title>far</title>
			<known>true</known>
		</word>
		<word>
			<title>feeling</title>
			<known>true</known>
		</word>
		<word>
			<title>fell</title>
			<known>true</known>
		</word>
		<word>
			<title>felt</title>
			<known>true</known>
		</word>
		<word>
			<title>few</title>
			<known>true</known>
		</word>
		<word>
			<title>find</title>
			<known>true</known>
		</word>
		<word>
			<title>force</title>
			<known>true</known>
		</word>
		<word>
			<title>found</title>
			<known>true</known>
		</word>
		<word>
			<title>fox</title>
			<known>true</known>
		</word>
		<word>
			<title>full</title>
			<known>true</known>
		</word>
		<word>
			<title>gave</title>
			<known>true</known>
		</word>
		<word>
			<title>get</title>
			<known>true</known>
		</word>
		<word>
			<title>girl</title>
			<known>true</known>
		</word>
		<word>
			<title>give</title>
			<known>true</known>
		</word>
		<word>
			<title>god</title>
			<known>true</known>
		</word>
		<word>
			<title>gone</title>
			<known>true</known>
		</word>
		<word>
			<title>good</title>
			<known>true</known>
		</word>
		<word>
			<title>got</title>
			<known>true</known>
		</word>
		<word>
			<title>great</title>
			<known>true</known>
		</word>
		<word>
			<title>half</title>
			<known>true</known>
		</word>
		<word>
			<title>hand</title>
			<known>true</known>
		</word>
		<word>
			<title>head</title>
			<known>true</known>
		</word>
		<word>
			<title>hear</title>
			<known>true</known>
		</word>
		<word>
			<title>heart</title>
			<known>true</known>
		</word>
		<word>
			<title>help</title>
			<known>true</known>
		</word>
		<word>
			<title>herself</title>
			<known>true</known>
		</word>
		<word>
			<title>history</title>
			<known>true</known>
		</word>
		<word>
			<title>hole</title>
			<known>true</known>
		</word>
		<word>
			<title>home</title>
			<known>true</known>
		</word>
		<word>
			<title>house</title>
			<known>true</known>
		</word>
		<word>
			<title>however</title>
			<known>true</known>
		</word>
		<word>
			<title>idea</title>
			<known>true</known>
		</word>
		<word>
			<title>keep</title>
			<known>true</known>
		</word>
		<word>
			<title>kind</title>
			<known>true</known>
		</word>
		<word>
			<title>large</title>
			<known>true</known>
		</word>
		<word>
			<title>later</title>
			<known>true</known>
		</word>
		<word>
			<title>least</title>
			<known>true</known>
		</word>
		<word>
			<title>left</title>
			<known>true</known>
		</word>
		<word>
			<title>let</title>
			<known>true</known>
		</word>
		<word>
			<title>life</title>
			<known>true</known>
		</word>
		<word>
			<title>light</title>
			<known>true</known>
		</word>
		<word>
			<title>long</title>
			<known>true</known>
		</word>
		<word>
			<title>look</title>
			<known>true</known>
		</word>
		<word>
			<title>many</title>
			<known>true</known>
		</word>
		<word>
			<title>matter</title>
			<known>true</known>
		</word>
		<word>
			<title>may</title>
			<known>true</known>
		</word>
		<word>
			<title>mean</title>
			<known>true</known>
		</word>
		<word>
			<title>men</title>
			<known>true</known>
		</word>
		<word>
			<title>million</title>
			<known>true</known>
		</word>
		<word>
			<title>mind</title>
			<known>true</known>
		</word>
		<word>
			<title>minute</title>
			<known>true</known>
		</word>
		<word>
			<title>moment</title>
			<known>true</known>
		</word>
		<word>
			<title>money</title>
			<known>true</known>
		</word>
		<word>
			<title>most</title>
			<known>true</known>
		</word>
		<word>
			<title>mother</title>
			<known>true</known>
		</word>
		<word>
			<title>myself</title>
			<known>true</known>
		</word>
		<word>
			<title>need</title>
			<known>true</known>
		</word>
		<word>
			<title>new</title>
			<known>true</known>
		</word>
		<word>
			<title>next</title>
			<known>true</known>
		</word>
		<word>
			<title>night</title>
			<known>true</known>
		</word>
		<word>
			<title>number</title>
			<known>true</known>
		</word>
		<word>
			<title>open</title>
			<known>true</known>
		</word>
		<word>
			<title>our</title>
			<known>true</known>
		</word>
		<word>
			<title>part</title>
			<known>true</known>
		</word>
		<word>
			<title>particle</title>
			<known>true</known>
		</word>
		<word>
			<title>party</title>
			<known>true</known>
		</word>
		<word>
			<title>past</title>
			<known>true</known>
		</word>
		<word>
			<title>people</title>
			<known>true</known>
		</word>
		<word>
			<title>perhaps</title>
			<known>true</known>
		</word>
		<word>
			<title>place</title>
			<known>true</known>
		</word>
		<word>
			<title>point</title>
			<known>true</known>
		</word>
		<word>
			<title>position</title>
			<known>true</known>
		</word>
		<word>
			<title>possible</title>
			<known>true</known>
		</word>
		<word>
			<title>present</title>
			<known>true</known>
		</word>
		<word>
			<title>put</title>
			<known>true</known>
		</word>
		<word>
			<title>question</title>
			<known>true</known>
		</word>
		<word>
			<title>quite</title>
			<known>true</known>
		</word>
		<word>
			<title>rather</title>
			<known>true</known>
		</word>
		<word>
			<title>real</title>
			<known>true</known>
		</word>
		<word>
			<title>really</title>
			<known>true</known>
		</word>
		<word>
			<title>remember</title>
			<known>true</known>
		</word>
		<word>
			<title>right</title>
			<known>true</known>
		</word>
		<word>
			<title>room</title>
			<known>true</known>
		</word>
		<word>
			<title>round</title>
			<known>true</known>
		</word>
		<word>
			<title>sat</title>
			<known>true</known>
		</word>
		<word>
			<title>saw</title>
			<known>true</known>
		</word>
		<word>
			<title>second</title>
			<known>true</known>
		</word>
		<word>
			<title>seen</title>
			<known>true</known>
		</word>
		<word>
			<title>set</title>
			<known>true</known>
		</word>
		<word>
			<title>shall</title>
			<known>true</known>
		</word>
		<word>
			<title>side</title>
			<known>true</known>
		</word>
		<word>
			<title>simply</title>
			<known>true</known>
		</word>
		<word>
			<title>since</title>
			<known>true</known>
		</word>
		<word>
			<title>sister</title>
			<known>true</known>
		</word>
		<word>
			<title>small</title>
			<known>true</known>
		</word>
		<word>
			<title>something</title>
			<known>true</known>
		</word>
		<word>
			<title>sometimes</title>
			<known>true</known>
		</word>
		<word>
			<title>soon</title>
			<known>true</known>
		</word>
		<word>
			<title>sort</title>
			<known>true</known>
		</word>
		<word>
			<title>space</title>
			<known>true</known>
		</word>
		<word>
			<title>speak</title>
			<known>true</known>
		</word>
		<word>
			<title>star</title>
			<known>true</known>
		</word>
		<word>
			<title>state</title>
			<known>true</known>
		</word>
		<word>
			<title>stood</title>
			<known>true</known>
		</word>
		<word>
			<title>strange</title>
			<known>true</known>
		</word>
		<word>
			<title>street</title>
			<known>true</known>
		</word>
		<word>
			<title>suddenly</title>
			<known>true</known>
		</word>
		<word>
			<title>sun</title>
			<known>true</known>
		</word>
		<word>
			<title>table</title>
			<known>true</known>
		</word>
		<word>
			<title>take</title>
			<known>true</known>
		</word>
		<word>
			<title>tell</title>
			<known>true</known>
		</word>
		<word>
			<title>ten</title>
			<known>true</known>
		</word>
		<word>
			<title>theory</title>
			<known>true</known>
		</word>
		<word>
			<title>therefore</title>
			<known>true</known>
		</word>
		<word>
			<title>thing</title>
			<known>true</known>
		</word>
		<word>
			<title>things</title>
			<known>true</known>
		</word>
		<word>
			<title>think</title>
			<known>true</known>
		</word>
		<word>
			<title>those</title>
			<known>true</known>
		</word>
		<word>
			<title>three</title>
			<known>true</known>
		</word>
		<word>
			<title>through</title>
			<known>true</known>
		</word>
		<word>
			<title>thus</title>
			<known>true</known>
		</word>
		<word>
			<title>times</title>
			<known>true</known>
		</word>
		<word>
			<title>together</title>
			<known>true</known>
		</word>
		<word>
			<title>told</title>
			<known>true</known>
		</word>
		<word>
			<title>took</title>
			<known>true</known>
		</word>
		<word>
			<title>true</title>
			<known>true</known>
		</word>
		<word>
			<title>under</title>
			<known>true</known>
		</word>
		<word>
			<title>understand</title>
			<known>true</known>
		</word>
		<word>
			<title>upon</title>
			<known>true</known>
		</word>
		<word>
			<title>use</title>
			<known>true</known>
		</word>
		<word>
			<title>used</title>
			<known>true</known>
		</word>
		<word>
			<title>voice</title>
			<known>true</known>
		</word>
		<word>
			<title>want</title>
			<known>true</known>
		</word>
		<word>
			<title>war</title>
			<known>true</known>
		</word>
		<word>
			<title>water</title>
			<known>true</known>
		</word>
		<word>
			<title>where</title>
			<known>true</known>
		</word>
		<word>
			<title>whether</title>
			<known>true</known>
		</word>
		<word>
			<title>while</title>
			<known>true</known>
		</word>
		<word>
			<title>whole</title>
			<known>true</known>
		</word>
		<word>
			<title>without</title>
			<known>true</known>
		</word>
		<word>
			<title>woman</title>
			<known>true</known>
		</word>
		<word>
			<title>word</title>
			<known>true</known>
		</word>
		<word>
			<title>work</title>
			<known>true</known>
		</word>
		<word>
			<title>world</title>
			<known>true</known>
		</word>
		<word>
			<title>yes</title>
			<known>true</known>
		</word>
		<word>
			<title>yesterday</title>
			<known>true</known>
		</word>
		<word>
			<title>yet</title>
			<known>true</known>
		</word>
		<word>
			<title>young</title>
			<known>true</known>
		</word>
		<word>
			<title>yourself</title>
			<known>true</known>
		</word>
	</second>
	<third>
		<word>
			<title>above</title>
			<known>true</known>
		</word>
		<word>
			<title>accept</title>
			<known>true</known>
		</word>
		<word>
			<title>account</title>
			<known>true</known>
		</word>
		<word>
			<title>act</title>
			<known>true</known>
		</word>
		<word>
			<title>actually</title>
			<known>true</known>
		</word>
		<word>
			<title>admit</title>
			<known>true</known>
		</word>
		<word>
			<title>afraid</title>
			<known>true</known>
		</word>
		<word>
			<title>age</title>
			<known>true</known>
		</word>
		<word>
			<title>agree</title>
			<known>true</known>
		</word>
		<word>
			<title>air</title>
			<known>true</known>
		</word>
		<word>
			<title>alive</title>
			<known>true</known>
		</word>
		<word>
			<title>allow</title>
			<known>true</known>
		</word>
		<word>
			<title>along</title>
			<known>true</known>
		</word>
		<word>
			<title>angry</title>
			<known>true</known>
		</word>
		<word>
			<title>answer</title>
			<known>true</known>
		</word>
		<word>
			<title>anxious</title>
			<known>true</known>
		</word>
		<word>
			<title>anyone</title>
			<known>true</known>
		</word>
		<word>
			<title>anyway</title>
			<known>true</known>
		</word>
		<word>
			<title>appear</title>
			<known>true</known>
		</word>
		<word>
			<title>appearance</title>
			<known>true</known>
		</word>
		<word>
			<title>arm</title>
			<known>true</known>
		</word>
		<word>
			<title>arms</title>
			<known>true</known>
		</word>
		<word>
			<title>around</title>
			<known>true</known>
		</word>
		<word>
			<title>arrow</title>
			<known>true</known>
		</word>
		<word>
			<title>article</title>
			<known>true</known>
		</word>
		<word>
			<title>ashamed</title>
			<known>true</known>
		</word>
		<word>
			<title>asleep</title>
			<known>true</known>
		</word>
		<word>
			<title>attention</title>
			<known>true</known>
		</word>
		<word>
			<title>attraction</title>
			<known>true</known>
		</word>
		<word>
			<title>avoid</title>
			<known>true</known>
		</word>
		<word>
			<title>aware</title>
			<known>true</known>
		</word>
		<word>
			<title>awful</title>
			<known>true</known>
		</word>
		<word>
			<title>bad</title>
			<known>true</known>
		</word>
		<word>
			<title>beat</title>
			<known>true</known>
		</word>
		<word>
			<title>became</title>
			<known>true</known>
		</word>
		<word>
			<title>bed</title>
			<known>true</known>
		</word>
		<word>
			<title>beg</title>
			<known>true</known>
		</word>
		<word>
			<title>begin</title>
			<known>true</known>
		</word>
		<word>
			<title>behind</title>
			<known>true</known>
		</word>
		<word>
			<title>beside</title>
			<known>true</known>
		</word>
		<word>
			<title>best</title>
			<known>true</known>
		</word>
		<word>
			<title>beyond</title>
			<known>true</known>
		</word>
		<word>
			<title>blood</title>
			<known>true</known>
		</word>
		<word>
			<title>blue</title>
			<known>true</known>
		</word>
		<word>
			<title>book</title>
			<known>true</known>
		</word>
		<word>
			<title>box</title>
			<known>true</known>
		</word>
		<word>
			<title>boy</title>
			<known>true</known>
		</word>
		<word>
			<title>brain</title>
			<known>true</known>
		</word>
		<word>
			<title>break</title>
			<known>true</known>
		</word>
		<word>
			<title>breath</title>
			<known>true</known>
		</word>
		<word>
			<title>bring</title>
			<known>true</known>
		</word>
		<word>
			<title>business</title>
			<known>true</known>
		</word>
		<word>
			<title>call</title>
			<known>true</known>
		</word>
		<word>
			<title>capable</title>
			<known>true</known>
		</word>
		<word>
			<title>care</title>
			<known>true</known>
		</word>
		<word>
			<title>careful</title>
			<known>true</known>
		</word>
		<word>
			<title>carry</title>
			<known>true</known>
		</word>
		<word>
			<title>catch</title>
			<known>true</known>
		</word>
		<word>
			<title>caught</title>
			<known>true</known>
		</word>
		<word>
			<title>cause</title>
			<known>true</known>
		</word>
		<word>
			<title>century</title>
			<known>true</known>
		</word>
		<word>
			<title>certainly</title>
			<known>true</known>
		</word>
		<word>
			<title>chair</title>
			<known>true</known>
		</word>
		<word>
			<title>chance</title>
			<known>true</known>
		</word>
		<word>
			<title>change</title>
			<known>true</known>
		</word>
		<word>
			<title>character</title>
			<known>true</known>
		</word>
		<word>
			<title>child</title>
			<known>true</known>
		</word>
		<word>
			<title>class</title>
			<known>true</known>
		</word>
		<word>
			<title>clear</title>
			<known>true</known>
		</word>
		<word>
			<title>close</title>
			<known>true</known>
		</word>
		<word>
			<title>cold</title>
			<known>true</known>
		</word>
		<word>
			<title>common</title>
			<known>true</known>
		</word>
		<word>
			<title>complete</title>
			<known>true</known>
		</word>
		<word>
			<title>condition</title>
			<known>true</known>
		</word>
		<word>
			<title>confess</title>
			<known>true</known>
		</word>
		<word>
			<title>conscious</title>
			<known>true</known>
		</word>
		<word>
			<title>consider</title>
			<known>true</known>
		</word>
		<word>
			<title>constant</title>
			<known>true</known>
		</word>
		<word>
			<title>contrary</title>
			<known>true</known>
		</word>
		<word>
			<title>control</title>
			<known>true</known>
		</word>
		<word>
			<title>conversation</title>
			<known>true</known>
		</word>
		<word>
			<title>corner</title>
			<known>true</known>
		</word>
		<word>
			<title>correct</title>
			<known>true</known>
		</word>
		<word>
			<title>country</title>
			<known>true</known>
		</word>
		<word>
			<title>couple</title>
			<known>true</known>
		</word>
		<word>
			<title>creature</title>
			<known>true</known>
		</word>
		<word>
			<title>crime</title>
			<known>true</known>
		</word>
		<word>
			<title>crow</title>
			<known>true</known>
		</word>
		<word>
			<title>cry</title>
			<known>true</known>
		</word>
		<word>
			<title>curious</title>
			<known>true</known>
		</word>
		<word>
			<title>cut</title>
			<known>true</known>
		</word>
		<word>
			<title>danger</title>
			<known>true</known>
		</word>
		<word>
			<title>dare</title>
			<known>true</known>
		</word>
		<word>
			<title>dark</title>
			<known>true</known>
		</word>
		<word>
			<title>date</title>
			<known>true</known>
		</word>
		<word>
			<title>daughter</title>
			<known>true</known>
		</word>
		<word>
			<title>dead</title>
			<known>true</known>
		</word>
		<word>
			<title>deal</title>
			<known>true</known>
		</word>
		<word>
			<title>dear</title>
			<known>true</known>
		</word>
		<word>
			<title>decide</title>
			<known>true</known>
		</word>
		<word>
			<title>deep</title>
			<known>true</known>
		</word>
		<word>
			<title>density</title>
			<known>true</known>
		</word>
		<word>
			<title>describe</title>
			<known>true</known>
		</word>
		<word>
			<title>desire</title>
			<known>true</known>
		</word>
		<word>
			<title>die</title>
			<known>true</known>
		</word>
		<word>
			<title>difference</title>
			<known>true</known>
		</word>
		<word>
			<title>difficult</title>
			<known>true</known>
		</word>
		<word>
			<title>difficulty</title>
			<known>true</known>
		</word>
		<word>
			<title>dinner</title>
			<known>true</known>
		</word>
		<word>
			<title>direction</title>
			<known>true</known>
		</word>
		<word>
			<title>directions</title>
			<known>true</known>
		</word>
		<word>
			<title>directly</title>
			<known>true</known>
		</word>
		<word>
			<title>dirty</title>
			<known>true</known>
		</word>
		<word>
			<title>discover</title>
			<known>true</known>
		</word>
		<word>
			<title>discovery</title>
			<known>true</known>
		</word>
		<word>
			<title>disorder</title>
			<known>true</known>
		</word>
		<word>
			<title>distance</title>
			<known>true</known>
		</word>
		<word>
			<title>dog</title>
			<known>true</known>
		</word>
		<word>
			<title>doorway</title>
			<known>true</known>
		</word>
		<word>
			<title>doubt</title>
			<known>true</known>
		</word>
		<word>
			<title>dream</title>
			<known>true</known>
		</word>
		<word>
			<title>dress</title>
			<known>true</known>
		</word>
		<word>
			<title>drew</title>
			<known>true</known>
		</word>
		<word>
			<title>drink</title>
			<known>true</known>
		</word>
		<word>
			<title>drunk</title>
			<known>true</known>
		</word>
		<word>
			<title>due</title>
			<known>true</known>
		</word>
		<word>
			<title>during</title>
			<known>true</known>
		</word>
		<word>
			<title>dust</title>
			<known>true</known>
		</word>
		<word>
			<title>duty</title>
			<known>true</known>
		</word>
		<word>
			<title>eagle</title>
			<known>true</known>
		</word>
		<word>
			<title>early</title>
			<known>true</known>
		</word>
		<word>
			<title>easily</title>
			<known>true</known>
		</word>
		<word>
			<title>easy</title>
			<known>true</known>
		</word>
		<word>
			<title>eat</title>
			<known>true</known>
		</word>
		<word>
			<title>edge</title>
			<known>true</known>
		</word>
		<word>
			<title>effect</title>
			<known>true</known>
		</word>
		<word>
			<title>effort</title>
			<known>true</known>
		</word>
		<word>
			<title>eight</title>
			<known>true</known>
		</word>
		<word>
			<title>either</title>
			<known>true</known>
		</word>
		<word>
			<title>else</title>
			<known>true</known>
		</word>
		<word>
			<title>empty</title>
			<known>true</known>
		</word>
		<word>
			<title>enemy</title>
			<known>true</known>
		</word>
		<word>
			<title>entirely</title>
			<known>true</known>
		</word>
		<word>
			<title>equal</title>
			<known>true</known>
		</word>
		<word>
			<title>escape</title>
			<known>true</known>
		</word>
		<word>
			<title>especially</title>
			<known>true</known>
		</word>
		<word>
			<title>evening</title>
			<known>true</known>
		</word>
		<word>
			<title>event</title>
			<known>true</known>
		</word>
		<word>
			<title>eventually</title>
			<known>true</known>
		</word>
		<word>
			<title>everyone</title>
			<known>true</known>
		</word>
		<word>
			<title>evidence</title>
			<known>true</known>
		</word>
		<word>
			<title>evidently</title>
			<known>true</known>
		</word>
		<word>
			<title>evil</title>
			<known>true</known>
		</word>
		<word>
			<title>exactly</title>
			<known>true</known>
		</word>
		<word>
			<title>example</title>
			<known>true</known>
		</word>
		<word>
			<title>except</title>
			<known>true</known>
		</word>
		<word>
			<title>excuse</title>
			<known>true</known>
		</word>
		<word>
			<title>exist</title>
			<known>true</known>
		</word>
		<word>
			<title>existence</title>
			<known>true</known>
		</word>
		<word>
			<title>expand</title>
			<known>true</known>
		</word>
		<word>
			<title>expansion</title>
			<known>true</known>
		</word>
		<word>
			<title>expect</title>
			<known>true</known>
		</word>
		<word>
			<title>explain</title>
			<known>true</known>
		</word>
		<word>
			<title>expression</title>
			<known>true</known>
		</word>
		<word>
			<title>faint</title>
			<known>true</known>
		</word>
		<word>
			<title>fairly</title>
			<known>true</known>
		</word>
		<word>
			<title>fall</title>
			<known>true</known>
		</word>
		<word>
			<title>family</title>
			<known>true</known>
		</word>
		<word>
			<title>fancy</title>
			<known>true</known>
		</word>
		<word>
			<title>fast</title>
			<known>true</known>
		</word>
		<word>
			<title>fate</title>
			<known>true</known>
		</word>
		<word>
			<title>father</title>
			<known>true</known>
		</word>
		<word>
			<title>fear</title>
			<known>true</known>
		</word>
		<word>
			<title>feel</title>
			<known>true</known>
		</word>
		<word>
			<title>feet</title>
			<known>true</known>
		</word>
		<word>
			<title>fellow</title>
			<known>true</known>
		</word>
		<word>
			<title>field</title>
			<known>true</known>
		</word>
		<word>
			<title>fifteen</title>
			<known>true</known>
		</word>
		<word>
			<title>figure</title>
			<known>true</known>
		</word>
		<word>
			<title>fill</title>
			<known>true</known>
		</word>
		<word>
			<title>finally</title>
			<known>true</known>
		</word>
		<word>
			<title>finger</title>
			<known>true</known>
		</word>
		<word>
			<title>fire</title>
			<known>true</known>
		</word>
		<word>
			<title>fit</title>
			<known>true</known>
		</word>
		<word>
			<title>five</title>
			<known>true</known>
		</word>
		<word>
			<title>fix</title>
			<known>true</known>
		</word>
		<word>
			<title>flat</title>
			<known>true</known>
		</word>
		<word>
			<title>floor</title>
			<known>true</known>
		</word>
		<word>
			<title>follow</title>
			<known>true</known>
		</word>
		<word>
			<title>food</title>
			<known>true</known>
		</word>
		<word>
			<title>fool</title>
			<known>true</known>
		</word>
		<word>
			<title>foot</title>
			<known>true</known>
		</word>
		<word>
			<title>forest</title>
			<known>true</known>
		</word>
		<word>
			<title>form</title>
			<known>true</known>
		</word>
		<word>
			<title>forth</title>
			<known>true</known>
		</word>
		<word>
			<title>forward</title>
			<known>true</known>
		</word>
		<word>
			<title>four</title>
			<known>true</known>
		</word>
		<word>
			<title>free</title>
			<known>true</known>
		</word>
		<word>
			<title>freedom</title>
			<known>true</known>
		</word>
		<word>
			<title>fresh</title>
			<known>true</known>
		</word>
		<word>
			<title>friend</title>
			<known>true</known>
		</word>
		<word>
			<title>frightened</title>
			<known>true</known>
		</word>
		<word>
			<title>front</title>
			<known>true</known>
		</word>
		<word>
			<title>fully</title>
			<known>true</known>
		</word>
		<word>
			<title>further</title>
			<known>true</known>
		</word>
		<word>
			<title>future</title>
			<known>true</known>
		</word>
		<word>
			<title>galaxy</title>
			<known>true</known>
		</word>
		<word>
			<title>gentleman</title>
			<known>true</known>
		</word>
		<word>
			<title>glad</title>
			<known>true</known>
		</word>
		<word>
			<title>glass</title>
			<known>true</known>
		</word>
		<word>
			<title>goes</title>
			<known>true</known>
		</word>
		<word>
			<title>gold</title>
			<known>true</known>
		</word>
		<word>
			<title>goodbye</title>
			<known>true</known>
		</word>
		<word>
			<title>gravity</title>
			<known>true</known>
		</word>
		<word>
			<title>greatly</title>
			<known>true</known>
		</word>
		<word>
			<title>green</title>
			<known>true</known>
		</word>
		<word>
			<title>grew</title>
			<known>true</known>
		</word>
		<word>
			<title>ground</title>
			<known>true</known>
		</word>
		<word>
			<title>grown</title>
			<known>true</known>
		</word>
		<word>
			<title>hair</title>
			<known>true</known>
		</word>
		<word>
			<title>happen</title>
			<known>true</known>
		</word>
		<word>
			<title>happy</title>
			<known>true</known>
		</word>
		<word>
			<title>hard</title>
			<known>true</known>
		</word>
		<word>
			<title>hardly</title>
			<known>true</known>
		</word>
		<word>
			<title>hat</title>
			<known>true</known>
		</word>
		<word>
			<title>hate</title>
			<known>true</known>
		</word>
		<word>
			<title>hear</title>
			<known>true</known>
		</word>
		<word>
			<title>heat</title>
			<known>true</known>
		</word>
		<word>
			<title>heavens</title>
			<known>true</known>
		</word>
		<word>
			<title>heavy</title>
			<known>true</known>
		</word>
		<word>
			<title>held</title>
			<known>true</known>
		</word>
		<word>
			<title>hide</title>
			<known>true</known>
		</word>
		<word>
			<title>high</title>
			<known>true</known>
		</word>
		<word>
			<title>hm</title>
			<known>true</known>
		</word>
		<word>
			<title>hold</title>
			<known>true</known>
		</word>
		<word>
			<title>holding</title>
			<known>true</known>
		</word>
		<word>
			<title>hope</title>
			<known>true</known>
		</word>
		<word>
			<title>horizon</title>
			<known>true</known>
		</word>
		<word>
			<title>horror</title>
			<known>true</known>
		</word>
		<word>
			<title>horse</title>
			<known>true</known>
		</word>
		<word>
			<title>hot</title>
			<known>true</known>
		</word>
		<word>
			<title>hour</title>
			<known>true</known>
		</word>
		<word>
			<title>huge</title>
			<known>true</known>
		</word>
		<word>
			<title>human</title>
			<known>true</known>
		</word>
		<word>
			<title>hundred</title>
			<known>true</known>
		</word>
		<word>
			<title>ill</title>
			<known>true</known>
		</word>
		<word>
			<title>illness</title>
			<known>true</known>
		</word>
		<word>
			<title>imaginary</title>
			<known>true</known>
		</word>
		<word>
			<title>imagine</title>
			<known>true</known>
		</word>
		<word>
			<title>immediately</title>
			<known>true</known>
		</word>
		<word>
			<title>important</title>
			<known>true</known>
		</word>
		<word>
			<title>impossible</title>
			<known>true</known>
		</word>
		<word>
			<title>impression</title>
			<known>true</known>
		</word>
		<word>
			<title>increase</title>
			<known>true</known>
		</word>
		<word>
			<title>infinite</title>
			<known>true</known>
		</word>
		<word>
			<title>initial</title>
			<known>true</known>
		</word>
		<word>
			<title>inside</title>
			<known>true</known>
		</word>
		<word>
			<title>instance</title>
			<known>true</known>
		</word>
		<word>
			<title>instant</title>
			<known>true</known>
		</word>
		<word>
			<title>instead</title>
			<known>true</known>
		</word>
		<word>
			<title>intelligent</title>
			<known>true</known>
		</word>
		<word>
			<title>intent</title>
			<known>true</known>
		</word>
		<word>
			<title>interest</title>
			<known>true</known>
		</word>
		<word>
			<title>interesting</title>
			<known>true</known>
		</word>
		<word>
			<title>interrupt</title>
			<known>true</known>
		</word>
		<word>
			<title>itself</title>
			<known>true</known>
		</word>
		<word>
			<title>job</title>
			<known>true</known>
		</word>
		<word>
			<title>kept</title>
			<known>true</known>
		</word>
		<word>
			<title>kill</title>
			<known>true</known>
		</word>
		<word>
			<title>knowledge</title>
			<known>true</known>
		</word>
		<word>
			<title>known</title>
			<known>true</known>
		</word>
		<word>
			<title>know</title>
			<known>true</known>
		</word>
		<word>
			<title>lady</title>
			<known>true</known>
		</word>
		<word>
			<title>laid</title>
			<known>true</known>
		</word>
		<word>
			<title>late</title>
			<known>true</known>
		</word>
		<word>
			<title>latter</title>
			<known>true</known>
		</word>
		<word>
			<title>laugh</title>
			<known>true</known>
		</word>
		<word>
			<title>law</title>
			<known>true</known>
		</word>
		<word>
			<title>lay</title>
			<known>true</known>
		</word>
		<word>
			<title>leave</title>
			<known>true</known>
		</word>
		<word>
			<title>led</title>
			<known>true</known>
		</word>
		<word>
			<title>less</title>
			<known>true</known>
		</word>
		<word>
			<title>letter</title>
			<known>true</known>
		</word>
		<word>
			<title>lie</title>
			<known>true</known>
		</word>
		<word>
			<title>likely</title>
			<known>true</known>
		</word>
		<word>
			<title>line</title>
			<known>true</known>
		</word>
		<word>
			<title>lip</title>
			<known>true</known>
		</word>
		<word>
			<title>listen</title>
			<known>true</known>
		</word>
		<word>
			<title>live</title>
			<known>true</known>
		</word>
		<word>
			<title>living</title>
			<known>true</known>
		</word>
		<word>
			<title>lose</title>
			<known>true</known>
		</word>
		<word>
			<title>lost</title>
			<known>true</known>
		</word>
		<word>
			<title>lot</title>
			<known>true</known>
		</word>
		<word>
			<title>love</title>
			<known>true</known>
		</word>
		<word>
			<title>low</title>
			<known>true</known>
		</word>
		<word>
			<title>lying</title>
			<known>true</known>
		</word>
		<word>
			<title>mad</title>
			<known>true</known>
		</word>
		<word>
			<title>making</title>
			<known>true</known>
		</word>
		<word>
			<title>man</title>
			<known>true</known>
		</word>
		<word>
			<title>marriage</title>
			<known>true</known>
		</word>
		<word>
			<title>marry</title>
			<known>true</known>
		</word>
		<word>
			<title>mass</title>
			<known>true</known>
		</word>
		<word>
			<title>master</title>
			<known>true</known>
		</word>
		<word>
			<title>maybe</title>
			<known>true</known>
		</word>
		<word>
			<title>meaning</title>
			<known>true</known>
		</word>
		<word>
			<title>meant</title>
			<known>true</known>
		</word>
		<word>
			<title>measure</title>
			<known>true</known>
		</word>
		<word>
			<title>meet</title>
			<known>true</known>
		</word>
		<word>
			<title>meeting</title>
			<known>true</known>
		</word>
		<word>
			<title>member</title>
			<known>true</known>
		</word>
		<word>
			<title>memory</title>
			<known>true</known>
		</word>
		<word>
			<title>mere</title>
			<known>true</known>
		</word>
		<word>
			<title>met</title>
			<known>true</known>
		</word>
		<word>
			<title>middle</title>
			<known>true</known>
		</word>
		<word>
			<title>mine</title>
			<known>true</known>
		</word>
		<word>
			<title>ministry</title>
			<known>true</known>
		</word>
		<word>
			<title>mistake</title>
			<known>true</known>
		</word>
		<word>
			<title>model</title>
			<known>true</known>
		</word>
		<word>
			<title>month</title>
			<known>true</known>
		</word>
		<word>
			<title>moreover</title>
			<known>true</known>
		</word>
		<word>
			<title>morning</title>
			<known>true</known>
		</word>
		<word>
			<title>mouse</title>
			<known>true</known>
		</word>
		<word>
			<title>mouth</title>
			<known>true</known>
		</word>
		<word>
			<title>move</title>
			<known>true</known>
		</word>
		<word>
			<title>movement</title>
			<known>true</known>
		</word>
		<word>
			<title>murder</title>
			<known>true</known>
		</word>
		<word>
			<title>mutter</title>
			<known>true</known>
		</word>
		<word>
			<title>name</title>
			<known>true</known>
		</word>
		<word>
			<title>natural</title>
			<known>true</known>
		</word>
		<word>
			<title>nature</title>
			<known>true</known>
		</word>
		<word>
			<title>near</title>
			<known>true</known>
		</word>
		<word>
			<title>nearly</title>
			<known>true</known>
		</word>
		<word>
			<title>necessary</title>
			<known>true</known>
		</word>
		<word>
			<title>neck</title>
			<known>true</known>
		</word>
		<word>
			<title>negative</title>
			<known>true</known>
		</word>
		<word>
			<title>neither</title>
			<known>true</known>
		</word>
		<word>
			<title>news</title>
			<known>true</known>
		</word>
		<word>
			<title>noise</title>
			<known>true</known>
		</word>
		<word>
			<title>nonsense</title>
			<known>true</known>
		</word>
		<word>
			<title>nor</title>
			<known>true</known>
		</word>
		<word>
			<title>normal</title>
			<known>true</known>
		</word>
		<word>
			<title>north</title>
			<known>true</known>
		</word>
		<word>
			<title>nose</title>
			<known>true</known>
		</word>
		<word>
			<title>note</title>
			<known>true</known>
		</word>
		<word>
			<title>notice</title>
			<known>true</known>
		</word>
		<word>
			<title>o</title>
			<known>true</known>
		</word>
		<word>
			<title>object</title>
			<known>true</known>
		</word>
		<word>
			<title>object</title>
			<known>true</known>
		</word>
		<word>
			<title>observation</title>
			<known>true</known>
		</word>
		<word>
			<title>observe</title>
			<known>true</known>
		</word>
		<word>
			<title>obviously</title>
			<known>true</known>
		</word>
		<word>
			<title>occur</title>
			<known>true</known>
		</word>
		<word>
			<title>office</title>
			<known>true</known>
		</word>
		<word>
			<title>often</title>
			<known>true</known>
		</word>
		<word>
			<title>opinion</title>
			<known>true</known>
		</word>
		<word>
			<title>opposite</title>
			<known>true</known>
		</word>
		<word>
			<title>order</title>
			<known>true</known>
		</word>
		<word>
			<title>ordinary</title>
			<known>true</known>
		</word>
		<word>
			<title>original</title>
			<known>true</known>
		</word>
		<word>
			<title>others</title>
			<known>true</known>
		</word>
		<word>
			<title>ought</title>
			<known>true</known>
		</word>
		<word>
			<title>outside</title>
			<known>true</known>
		</word>
		<word>
			<title>paid</title>
			<known>true</known>
		</word>
		<word>
			<title>pain</title>
			<known>true</known>
		</word>
		<word>
			<title>pale</title>
			<known>true</known>
		</word>
		<word>
			<title>paper</title>
			<known>true</known>
		</word>
		<word>
			<title>particle</title>
			<known>true</known>
		</word>
		<word>
			<title>particular</title>
			<known>true</known>
		</word>
		<word>
			<title>particularly</title>
			<known>true</known>
		</word>
		<word>
			<title>partly</title>
			<known>true</known>
		</word>
		<word>
			<title>pass</title>
			<known>true</known>
		</word>
		<word>
			<title>passage</title>
			<known>true</known>
		</word>
		<word>
			<title>passing</title>
			<known>true</known>
		</word>
		<word>
			<title>pay</title>
			<known>true</known>
		</word>
		<word>
			<title>peace</title>
			<known>true</known>
		</word>
		<word>
			<title>peculiar</title>
			<known>true</known>
		</word>
		<word>
			<title>per</title>
			<known>true</known>
		</word>
		<word>
			<title>perfect</title>
			<known>true</known>
		</word>
		<word>
			<title>perfectly</title>
			<known>true</known>
		</word>
		<word>
			<title>person</title>
			<known>true</known>
		</word>
		<word>
			<title>picture</title>
			<known>true</known>
		</word>
		<word>
			<title>piece</title>
			<known>true</known>
		</word>
		<word>
			<title>please</title>
			<known>true</known>
		</word>
		<word>
			<title>pleasure</title>
			<known>true</known>
		</word>
		<word>
			<title>pocket</title>
			<known>true</known>
		</word>
		<word>
			<title>police</title>
			<known>true</known>
		</word>
		<word>
			<title>poor</title>
			<known>true</known>
		</word>
		<word>
			<title>porter</title>
			<known>true</known>
		</word>
		<word>
			<title>positive</title>
			<known>true</known>
		</word>
		<word>
			<title>possibility</title>
			<known>true</known>
		</word>
		<word>
			<title>possibly</title>
			<known>true</known>
		</word>
		<word>
			<title>power</title>
			<known>true</known>
		</word>
		<word>
			<title>pray</title>
			<known>true</known>
		</word>
		<word>
			<title>predict</title>
			<known>true</known>
		</word>
		<word>
			<title>pretty</title>
			<known>true</known>
		</word>
		<word>
			<title>principle</title>
			<known>true</known>
		</word>
		<word>
			<title>prison</title>
			<known>true</known>
		</word>
		<word>
			<title>probably</title>
			<known>true</known>
		</word>
		<word>
			<title>problem</title>
			<known>true</known>
		</word>
		<word>
			<title>process</title>
			<known>true</known>
		</word>
		<word>
			<title>produce</title>
			<known>true</known>
		</word>
		<word>
			<title>public</title>
			<known>true</known>
		</word>
		<word>
			<title>pull</title>
			<known>true</known>
		</word>
		<word>
			<title>purpose</title>
			<known>true</known>
		</word>
		<word>
			<title>pushed</title>
			<known>true</known>
		</word>
		<word>
			<title>quickly</title>
			<known>true</known>
		</word>
		<word>
			<title>raise</title>
			<known>true</known>
		</word>
		<word>
			<title>ran</title>
			<known>true</known>
		</word>
		<word>
			<title>rate</title>
			<known>true</known>
		</word>
		<word>
			<title>ray</title>
			<known>true</known>
		</word>
		<word>
			<title>reach</title>
			<known>true</known>
		</word>
		<word>
			<title>read</title>
			<known>true</known>
		</word>
		<word>
			<title>reading</title>
			<known>true</known>
		</word>
		<word>
			<title>ready</title>
			<known>true</known>
		</word>
		<word>
			<title>reality</title>
			<known>true</known>
		</word>
		<word>
			<title>realize</title>
			<known>true</known>
		</word>
		<word>
			<title>reason</title>
			<known>true</known>
		</word>
		<word>
			<title>receive</title>
			<known>true</known>
		</word>
		<word>
			<title>record</title>
			<known>true</known>
		</word>
		<word>
			<title>red</title>
			<known>true</known>
		</word>
		<word>
			<title>region</title>
			<known>true</known>
		</word>
		<word>
			<title>regular</title>
			<known>true</known>
		</word>
		<word>
			<title>remain</title>
			<known>true</known>
		</word>
		<word>
			<title>repeated</title>
			<known>true</known>
		</word>
		<word>
			<title>reply</title>
			<known>true</known>
		</word>
		<word>
			<title>request</title>
			<known>true</known>
		</word>
		<word>
			<title>respect</title>
			<known>true</known>
		</word>
		<word>
			<title>rest</title>
			<known>true</known>
		</word>
		<word>
			<title>result</title>
			<known>true</known>
		</word>
		<word>
			<title>return</title>
			<known>true</known>
		</word>
		<word>
			<title>revolution</title>
			<known>true</known>
		</word>
		<word>
			<title>rich</title>
			<known>true</known>
		</word>
		<word>
			<title>rose</title>
			<known>true</known>
		</word>
		<word>
			<title>run</title>
			<known>true</known>
		</word>
		<word>
			<title>rush</title>
			<known>true</known>
		</word>
		<word>
			<title>sake</title>
			<known>true</known>
		</word>
		<word>
			<title>sank</title>
			<known>true</known>
		</word>
		<word>
			<title>scarcely</title>
			<known>true</known>
		</word>
		<word>
			<title>science</title>
			<known>true</known>
		</word>
		<word>
			<title>scientific</title>
			<known>true</known>
		</word>
		<word>
			<title>search</title>
			<known>true</known>
		</word>
		<word>
			<title>secret</title>
			<known>true</known>
		</word>
		<word>
			<title>seem</title>
			<known>true</known>
		</word>
		<word>
			<title>seize</title>
			<known>true</known>
		</word>
		<word>
			<title>send</title>
			<known>true</known>
		</word>
		<word>
			<title>sensation</title>
			<known>true</known>
		</word>
		<word>
			<title>sense</title>
			<known>true</known>
		</word>
		<word>
			<title>sent</title>
			<known>true</known>
		</word>
		<word>
			<title>settled</title>
			<known>true</known>
		</word>
		<word>
			<title>seven</title>
			<known>true</known>
		</word>
		<word>
			<title>several</title>
			<known>true</known>
		</word>
		<word>
			<title>shake</title>
			<known>true</known>
		</word>
		<word>
			<title>sheep</title>
			<known>true</known>
		</word>
		<word>
			<title>short</title>
			<known>true</known>
		</word>
		<word>
			<title>shoulder</title>
			<known>true</known>
		</word>
		<word>
			<title>show</title>
			<known>true</known>
		</word>
		<word>
			<title>shown</title>
			<known>true</known>
		</word>
		<word>
			<title>shut</title>
			<known>true</known>
		</word>
		<word>
			<title>sick</title>
			<known>true</known>
		</word>
		<word>
			<title>sight</title>
			<known>true</known>
		</word>
		<word>
			<title>sign</title>
			<known>true</known>
		</word>
		<word>
			<title>silence</title>
			<known>true</known>
		</word>
		<word>
			<title>silent</title>
			<known>true</known>
		</word>
		<word>
			<title>similar</title>
			<known>true</known>
		</word>
		<word>
			<title>simple</title>
			<known>true</known>
		</word>
		<word>
			<title>singing</title>
			<known>true</known>
		</word>
		<word>
			<title>single</title>
			<known>true</known>
		</word>
		<word>
			<title>sir</title>
			<known>true</known>
		</word>
		<word>
			<title>sit</title>
			<known>true</known>
		</word>
		<word>
			<title>six</title>
			<known>true</known>
		</word>
		<word>
			<title>size</title>
			<known>true</known>
		</word>
		<word>
			<title>sleep</title>
			<known>true</known>
		</word>
		<word>
			<title>slightly</title>
			<known>true</known>
		</word>
		<word>
			<title>slow</title>
			<known>true</known>
		</word>
		<word>
			<title>slowly</title>
			<known>true</known>
		</word>
		<word>
			<title>smell</title>
			<known>true</known>
		</word>
		<word>
			<title>smile</title>
			<known>true</known>
		</word>
		<word>
			<title>smooth</title>
			<known>true</known>
		</word>
		<word>
			<title>society</title>
			<known>true</known>
		</word>
		<word>
			<title>somehow</title>
			<known>true</known>
		</word>
		<word>
			<title>someone</title>
			<known>true</known>
		</word>
		<word>
			<title>somewhere</title>
			<known>true</known>
		</word>
		<word>
			<title>son</title>
			<known>true</known>
		</word>
		<word>
			<title>sorry</title>
			<known>true</known>
		</word>
		<word>
			<title>soul</title>
			<known>true</known>
		</word>
		<word>
			<title>sound</title>
			<known>true</known>
		</word>
		<word>
			<title>special</title>
			<known>true</known>
		</word>
		<word>
			<title>speech</title>
			<known>true</known>
		</word>
		<word>
			<title>speed</title>
			<known>true</known>
		</word>
		<word>
			<title>spent</title>
			<known>true</known>
		</word>
		<word>
			<title>spin</title>
			<known>true</known>
		</word>
		<word>
			<title>spite</title>
			<known>true</known>
		</word>
		<word>
			<title>spoke</title>
			<known>true</known>
		</word>
		<word>
			<title>spoken</title>
			<known>true</known>
		</word>
		<word>
			<title>spot</title>
			<known>true</known>
		</word>
		<word>
			<title>stand</title>
			<known>true</known>
		</word>
		<word>
			<title>star</title>
			<known>true</known>
		</word>
		<word>
			<title>start</title>
			<known>true</known>
		</word>
		<word>
			<title>stay</title>
			<known>true</known>
		</word>
		<word>
			<title>step</title>
			<known>true</known>
		</word>
		<word>
			<title>stone</title>
			<known>true</known>
		</word>
		<word>
			<title>stop</title>
			<known>true</known>
		</word>
		<word>
			<title>story</title>
			<known>true</known>
		</word>
		<word>
			<title>straight</title>
			<known>true</known>
		</word>
		<word>
			<title>strength</title>
			<known>true</known>
		</word>
		<word>
			<title>string</title>
			<known>true</known>
		</word>
		<word>
			<title>strong</title>
			<known>true</known>
		</word>
		<word>
			<title>struck</title>
			<known>true</known>
		</word>
		<word>
			<title>student</title>
			<known>true</known>
		</word>
		<word>
			<title>stupid</title>
			<known>true</known>
		</word>
		<word>
			<title>subject</title>
			<known>true</known>
		</word>
		<word>
			<title>succeed</title>
			<known>true</known>
		</word>
		<word>
			<title>sudden</title>
			<known>true</known>
		</word>
		<word>
			<title>suffering</title>
			<known>true</known>
		</word>
		<word>
			<title>suggest</title>
			<known>true</known>
		</word>
		<word>
			<title>sum</title>
			<known>true</known>
		</word>
		<word>
			<title>suppose</title>
			<known>true</known>
		</word>
		<word>
			<title>supposed</title>
			<known>true</known>
		</word>
		<word>
			<title>sure</title>
			<known>true</known>
		</word>
		<word>
			<title>surface</title>
			<known>true</known>
		</word>
		<word>
			<title>surprise</title>
			<known>true</known>
		</word>
		<word>
			<title>suspicion</title>
			<known>true</known>
		</word>
		<word>
			<title>system</title>
			<known>true</known>
		</word>
		<word>
			<title>talk</title>
			<known>true</known>
		</word>
		<word>
			<title>tea</title>
			<known>true</known>
		</word>
		<word>
			<title>tear</title>
			<known>true</known>
		</word>
		<word>
			<title>teeth</title>
			<known>true</known>
		</word>
		<word>
			<title>telling</title>
			<known>true</known>
		</word>
		<word>
			<title>temperature</title>
			<known>true</known>
		</word>
		<word>
			<title>terrible</title>
			<known>true</known>
		</word>
		<word>
			<title>terror</title>
			<known>true</known>
		</word>
		<word>
			<title>themselves</title>
			<known>true</known>
		</word>
		<word>
			<title>thick</title>
			<known>true</known>
		</word>
		<word>
			<title>thin</title>
			<known>true</known>
		</word>
		<word>
			<title>third</title>
			<known>true</known>
		</word>
		<word>
			<title>thirty</title>
			<known>true</known>
		</word>
		<word>
			<title>thought</title>
			<known>true</known>
		</word>
		<word>
			<title>thousand</title>
			<known>true</known>
		</word>
		<word>
			<title>threw</title>
			<known>true</known>
		</word>
		<word>
			<title>throw</title>
			<known>true</known>
		</word>
		<word>
			<title>till</title>
			<known>true</known>
		</word>
		<word>
			<title>tiny</title>
			<known>true</known>
		</word>
		<word>
			<title>today</title>
			<known>true</known>
		</word>
		<word>
			<title>tomorrow</title>
			<known>true</known>
		</word>
		<word>
			<title>top</title>
			<known>true</known>
		</word>
		<word>
			<title>torn</title>
			<known>true</known>
		</word>
		<word>
			<title>torture</title>
			<known>true</known>
		</word>
		<word>
			<title>touch</title>
			<known>true</known>
		</word>
		<word>
			<title>town</title>
			<known>true</known>
		</word>
		<word>
			<title>travel</title>
			<known>true</known>
		</word>
		<word>
			<title>tree</title>
			<known>true</known>
		</word>
		<word>
			<title>trouble</title>
			<known>true</known>
		</word>
		<word>
			<title>truth</title>
			<known>true</known>
		</word>
		<word>
			<title>try</title>
			<known>true</known>
		</word>
		<word>
			<title>turn</title>
			<known>true</known>
		</word>
		<word>
			<title>twenty</title>
			<known>true</known>
		</word>
		<word>
			<title>twice</title>
			<known>true</known>
		</word>
		<word>
			<title>unable</title>
			<known>true</known>
		</word>
		<word>
			<title>uniform</title>
			<known>true</known>
		</word>
		<word>
			<title>until</title>
			<known>true</known>
		</word>
		<word>
			<title>usual</title>
			<known>true</known>
		</word>
		<word>
			<title>value</title>
			<known>true</known>
		</word>
		<word>
			<title>various</title>
			<known>true</known>
		</word>
		<word>
			<title>vast</title>
			<known>false</known>
		</word>
		<word>
			<title>victory</title>
			<known>true</known>
		</word>
		<word>
			<title>view</title>
			<known>true</known>
		</word>
		<word>
			<title>visit</title>
			<known>true</known>
		</word>
		<word>
			<title>visitor</title>
			<known>true</known>
		</word>
		<word>
			<title>wait</title>
			<known>true</known>
		</word>
		<word>
			<title>walk</title>
			<known>true</known>
		</word>
		<word>
			<title>wall</title>
			<known>true</known>
		</word>
		<word>
			<title>warm</title>
			<known>true</known>
		</word>
		<word>
			<title>watch</title>
			<known>true</known>
		</word>
		<word>
			<title>wave</title>
			<known>true</known>
		</word>
		<word>
			<title>weak</title>
			<known>true</known>
		</word>
		<word>
			<title>week</title>
			<known>true</known>
		</word>
		<word>
			<title>whatever</title>
			<known>true</known>
		</word>
		<word>
			<title>whisper</title>
			<known>true</known>
		</word>
		<word>
			<title>white</title>
			<known>true</known>
		</word>
		<word>
			<title>whom</title>
			<known>true</known>
		</word>
		<word>
			<title>whose</title>
			<known>true</known>
		</word>
		<word>
			<title>wide</title>
			<known>true</known>
		</word>
		<word>
			<title>wife</title>
			<known>true</known>
		</word>
		<word>
			<title>wind</title>
			<known>true</known>
		</word>
		<word>
			<title>window</title>
			<known>true</known>
		</word>
		<word>
			<title>wish</title>
			<known>true</known>
		</word>
		<word>
			<title>within</title>
			<known>true</known>
		</word>
		<word>
			<title>wolf</title>
			<known>true</known>
		</word>
		<word>
			<title>women</title>
			<known>true</known>
		</word>
		<word>
			<title>wood</title>
			<known>true</known>
		</word>
		<word>
			<title>worry</title>
			<known>true</known>
		</word>
		<word>
			<title>worth</title>
			<known>true</known>
		</word>
		<word>
			<title>write</title>
			<known>true</known>
		</word>
		<word>
			<title>wrong</title>
			<known>true</known>
		</word>
		<word>
			<title>year</title>
			<known>true</known>
		</word>
		<word>
			<title>yellow</title>
			<known>true</known>
		</word>
	</third>
</main>
